{
    "Ar36": {
        "error": 0.00011772399885511536, 
        "fit": "previous", 
        "references": [
            {
                "exclude": false, 
                "record_id": "bc-02-F-276"
            }
        ], 
        "value": 0.0016301326580839973
    }, 
    "Ar37": {
        "error": 0.011649251674152563, 
        "fit": "previous", 
        "references": [
            {
                "exclude": false, 
                "record_id": "bc-02-F-276"
            }
        ], 
        "value": -0.0033981306052113247
    }, 
    "Ar38": {
        "error": 0.013092778737744209, 
        "fit": "previous", 
        "references": [
            {
                "exclude": false, 
                "record_id": "bc-02-F-276"
            }
        ], 
        "value": 0.01746937076237577
    }, 
    "Ar39": {
        "error": 0.026242214762214566, 
        "fit": "previous", 
        "references": [
            {
                "exclude": false, 
                "record_id": "bc-02-F-276"
            }
        ], 
        "value": -0.035751423727427595
    }, 
    "Ar40": {
        "error": 0.019872118259330482, 
        "fit": "previous", 
        "references": [
            {
                "exclude": false, 
                "record_id": "bc-02-F-276"
            }
        ], 
        "value": 0.46050966144153654
    }
}