{
    "Ar36": {
        "error": 0.0003064293029786717, 
        "filter_outliers_dict": {
            "filter_outliers": true, 
            "iterations": 2, 
            "std_devs": 2
        }, 
        "fit": "Parabolic", 
        "value": 0.001678626078164204
    }, 
    "Ar36H": {
        "error": 0.0015981016427274322, 
        "filter_outliers_dict": {
            "filter_outliers": true, 
            "iterations": 2, 
            "std_devs": 2
        }, 
        "fit": "Parabolic", 
        "value": 0.0439147085960918
    }, 
    "Ar37": {
        "error": 0.0001252790667832026, 
        "filter_outliers_dict": {
            "filter_outliers": true, 
            "iterations": 2, 
            "std_devs": 2
        }, 
        "fit": "linear", 
        "value": 0.003108673889342933
    }, 
    "Ar37H": {
        "error": 0.0012944790794002944, 
        "filter_outliers_dict": {
            "filter_outliers": true, 
            "iterations": 2, 
            "std_devs": 2
        }, 
        "fit": "linear", 
        "value": 0.08775686126563623
    }, 
    "Ar38": {
        "error": 0.0001064581528198691, 
        "filter_outliers_dict": {
            "filter_outliers": true, 
            "iterations": 2, 
            "std_devs": 2
        }, 
        "fit": "linear", 
        "value": 0.0006821128514237794
    }, 
    "Ar38H": {
        "error": 0.0014417180368031643, 
        "filter_outliers_dict": {
            "filter_outliers": true, 
            "iterations": 2, 
            "std_devs": 2
        }, 
        "fit": "linear", 
        "value": 0.07398819366837761
    }, 
    "Ar39": {
        "error": 0.0004339229638776937, 
        "filter_outliers_dict": {
            "filter_outliers": true, 
            "iterations": 2, 
            "std_devs": 2
        }, 
        "fit": "Parabolic", 
        "value": 0.00238275271100686
    }, 
    "Ar39H": {
        "error": 0.00600825369495132, 
        "filter_outliers_dict": {
            "filter_outliers": true, 
            "iterations": 2, 
            "std_devs": 2
        }, 
        "fit": "Parabolic", 
        "value": 0.1710281299867393
    }, 
    "Ar40": {
        "error": 0.037140471343856146, 
        "filter_outliers_dict": {
            "filter_outliers": true, 
            "iterations": 2, 
            "std_devs": 2
        }, 
        "fit": "Parabolic", 
        "value": 0.04884010678968713
    }, 
    "Ar40H": {
        "error": 0.001208801862405484, 
        "filter_outliers_dict": {
            "filter_outliers": true, 
            "iterations": 2, 
            "std_devs": 2
        }, 
        "fit": "Parabolic", 
        "value": 0.03205742225623209
    }, 
    "HCl": {
        "error": 0.00039008834899497774, 
        "filter_outliers_dict": {
            "filter_outliers": true, 
            "iterations": 2, 
            "std_devs": 2
        }, 
        "fit": "Parabolic", 
        "value": 0.0001176302001075147
    }, 
    "Iso36.8624": {
        "error": 0.0, 
        "filter_outliers_dict": {
            "filter_outliers": false, 
            "iterations": 1, 
            "std_devs": 2
        }, 
        "fit": "linear", 
        "value": 0.0360602147158054
    }, 
    "Iso37.8624": {
        "error": 0.0, 
        "filter_outliers_dict": {
            "filter_outliers": false, 
            "iterations": 1, 
            "std_devs": 2
        }, 
        "fit": "linear", 
        "value": 0.0
    }, 
    "Iso39.8624": {
        "error": 0.0, 
        "filter_outliers_dict": {
            "filter_outliers": false, 
            "iterations": 1, 
            "std_devs": 2
        }, 
        "fit": "linear", 
        "value": 0.0
    }, 
    "PHHCbs": {
        "error": 0.0, 
        "filter_outliers_dict": {
            "filter_outliers": false, 
            "iterations": 1, 
            "std_devs": 2
        }, 
        "fit": "linear", 
        "value": 0.0
    }
}